elizabeth/__init__.py
elizabeth/data_class.py
elizabeth/executor.py
elizabeth-0.0.2.dist-info/METADATA
elizabeth-0.0.2.dist-info/WHEEL
elizabeth-0.0.2.dist-info/top_level.txt
elizabeth-0.0.2.dist-info/RECORD
