Metadata-Version: 2.1
Name: elizabeth
Version: 0.0.2
Summary: Machine leaning pipeline
Home-page: https://github.com/marubontan/elizabeth
Author: Shuhei Kishi
Author-email: marubontan@gmail.com
License: MIT
Platform: UNKNOWN
